dockenv/__init__.py
dockenv/__main__.py
dockenv/dockenv.py
dockenv/pip_freeze.py
dockenv_cli-1.0.0.dist-info/LICENSE
dockenv_cli-1.0.0.dist-info/METADATA
dockenv_cli-1.0.0.dist-info/WHEEL
dockenv_cli-1.0.0.dist-info/entry_points.txt
dockenv_cli-1.0.0.dist-info/top_level.txt
dockenv_cli-1.0.0.dist-info/RECORD
